gist_import/__init__.py
gist_import/execution.py
gist_import/imports.py
gist_import-1.0.3.dist-info/LICENSE
gist_import-1.0.3.dist-info/METADATA
gist_import-1.0.3.dist-info/WHEEL
gist_import-1.0.3.dist-info/top_level.txt
gist_import-1.0.3.dist-info/RECORD
